{
  "parent": "minecraft:recipes/root",
  "rewards": {
    "recipes": [
      "packed:spruce_crate_default"
    ]
  },
  "criteria": {
    "has_chest": {
      "trigger": "minecraft:inventory_changed",
      "conditions": {
        "items": [
          {
            "item": "packed:spruce_chest_default",
            "count" :  {
              "min": 4,
              "max" : 64
            }
          }
        ]
      }
    },
    "has_the_recipe": {
      "trigger": "minecraft:recipe_unlocked",
      "conditions": {
        "recipe": "packed:spruce_crate_default"
      }
    }
  },
  "requirements": [
    [
      "has_chest",
      "has_the_recipe"
    ]
  ]
}