{
    "type": "minecraft:crafting_shaped",
    "pattern": [
        "#i#",
        "#P#",
        "#_#"
    ],
    "key": {
        "#": {
            "item": "minecraft:crimson_planks"
        },
        "i": {
            "item": "minecraft:diamond"
        },
        "P": {
            "item": "packed:crimson_barrel_tier2"
        },
        "_": {
            "item": "minecraft:crimson_slab"
        }
    },
    "result": {
        "item": "packed:crimson_barrel_tier3",
        "count": 1
    },
    "group": "barrel_tier3"
}
